csvstat/__init__.py
csvstat/csv.py
csvstat/setup.py
csvstat-1.1.dist-info/METADATA
csvstat-1.1.dist-info/WHEEL
csvstat-1.1.dist-info/top_level.txt
csvstat-1.1.dist-info/RECORD
